ytwrap/__init__.py
ytwrap/analysi.py
ytwrap/channel.py
ytwrap/comment.py
ytwrap/streams.py
ytwrap/subscribe.py
ytwrap/utils.py
ytwrap/video.py
ytwrap-0.2.5.dist-info/LICENSE
ytwrap-0.2.5.dist-info/METADATA
ytwrap-0.2.5.dist-info/WHEEL
ytwrap-0.2.5.dist-info/top_level.txt
ytwrap-0.2.5.dist-info/RECORD
