Metadata-Version: 2.1
Name: ytwrap
Version: 0.2.5
Summary: Python wrapper for the YouTube Data API v3.
Home-page: https://github.com/Himarry/ytwrap
Author: Himarry
Project-URL: Source, https://github.com/Himarry/ytwrap
Project-URL: Tracker, https://github.com/Himarry/ytwrap/issues
Classifier: Programming Language :: Python :: 3
Classifier: Programming Language :: Python :: 3.7
Classifier: Programming Language :: Python :: 3.8
Classifier: Programming Language :: Python :: 3.9
Classifier: Programming Language :: Python :: 3.10
Classifier: Programming Language :: Python :: 3.11
Classifier: Programming Language :: Python :: 3.12
Requires-Python: >=3.7
License-File: LICENSE
Requires-Dist: google-api-python-client
Requires-Dist: isodate
Requires-Dist: pytz
